dungngo_unichat_mcp_server-0.2.21.dist-info/licenses/LICENSE
unichat_mcp_server/__init__.py
unichat_mcp_server/server.py
dungngo_unichat_mcp_server-0.2.21.dist-info/METADATA
dungngo_unichat_mcp_server-0.2.21.dist-info/WHEEL
dungngo_unichat_mcp_server-0.2.21.dist-info/entry_points.txt
dungngo_unichat_mcp_server-0.2.21.dist-info/top_level.txt
dungngo_unichat_mcp_server-0.2.21.dist-info/RECORD
