Metadata-Version: 2.4
Name: dungngo-unichat-mcp-server
Version: 0.2.21
Summary: Unichat MCP Server (republished for testing)
Author-email: dungngo <test@dungngo.dev>
Requires-Python: >=3.11
License-File: LICENSE
Requires-Dist: mcp>=1.0.0
Requires-Dist: unichat~=3.6.0
Dynamic: license-file
